gha_python_packaging_demo_ra/__init__.py
gha_python_packaging_demo_ra/app.py
gha_python_packaging_demo_ra-0.0.3.dist-info/LICENSE
gha_python_packaging_demo_ra-0.0.3.dist-info/METADATA
gha_python_packaging_demo_ra-0.0.3.dist-info/WHEEL
gha_python_packaging_demo_ra-0.0.3.dist-info/entry_points.txt
gha_python_packaging_demo_ra-0.0.3.dist-info/top_level.txt
gha_python_packaging_demo_ra-0.0.3.dist-info/RECORD
