Metadata-Version: 2.1
Name: gha-python-packaging-demo-ra
Version: 0.0.3
Summary: Demo of a simple way to use GitHub Actions to build your Python package, bump the version number, and publish it to GitHub releases and PyPI.org all with a single click of a button in the web interface.
Home-page: https://github.com/RachelAlcraft/gha-python-packaging-demo
Project-URL: Bug Tracker, https://github.com/RachelAlcraft/gha-python-packaging-demo/issues
Project-URL: Changelog, https://github.com/RachelAlcraft/gha-python-packaging-demo/releases
Classifier: Programming Language :: Python :: 3
Classifier: License :: OSI Approved :: BSD License
Classifier: Intended Audience :: Developers
Requires-Python: >=3.6
License-File: LICENSE
